ml_loader/__init__.py
ml_loader/file_loader.py
ml_loader-0.1.dist-info/LICENSE
ml_loader-0.1.dist-info/METADATA
ml_loader-0.1.dist-info/WHEEL
ml_loader-0.1.dist-info/top_level.txt
ml_loader-0.1.dist-info/RECORD
