Metadata-Version: 2.1
Name: ml_loader
Version: 0.1
Summary: A package to load data files based on their file extension.
Home-page: https://github.com/sazib0/ml_loader
Author: Sazib
Author-email: sazibc5@gmail.com
Classifier: Programming Language :: Python :: 3
Classifier: License :: OSI Approved :: BSD License
Classifier: Operating System :: OS Independent
Requires-Python: >=3.6
License-File: LICENSE
Requires-Dist: pandas
Requires-Dist: pyreadstat
Requires-Dist: pillow
Requires-Dist: sqlalchemy
Requires-Dist: lxml
